{
  "free_tier": {
    "mes": "2026-06",
    "vcpu_used": 908953,
    "vcpu_free": 180000,
    "gib_used": 454476,
    "gib_free": 360000,
    "req_used": 3018,
    "req_free": 2000000,
    "cobranca_mes": 102.13,
    "dentro_do_free": false
  },
  "generated_at": "2026-06-25 22:19 UTC",
  "fonte": "Cloud Monitoring (tempo quase real). Custo é ESTIMADO a partir do tempo faturável de CPU/memória do Cloud Run.",
  "data_source": "monitoring",
  "last_data_day": "2026-06-25",
  "period": {
    "start": "2026-06-11",
    "end": "2026-06-25"
  },
  "currency": "BRL",
  "total": 18.39,
  "by_mcp": [
    {
      "mcp": "oplab-sheets-mcp",
      "requisicoes": 586,
      "billable_segundos": 68253,
      "custo_liquido": 9.93,
      "custo_por_requisicao": 0.01694
    },
    {
      "mcp": "oplab-mcp-server",
      "requisicoes": 717,
      "billable_segundos": 58180,
      "custo_liquido": 8.46,
      "custo_por_requisicao": 0.011802
    }
  ],
  "by_mcp_day": [
    {
      "mcp": "oplab-mcp-server",
      "dia": "2026-06-13",
      "custo": 0.0,
      "chamadas": 15
    },
    {
      "mcp": "oplab-mcp-server",
      "dia": "2026-06-20",
      "custo": 0.0,
      "chamadas": 15
    },
    {
      "mcp": "oplab-mcp-server",
      "dia": "2026-06-24",
      "custo": 0.02,
      "chamadas": 147
    },
    {
      "mcp": "oplab-mcp-server",
      "dia": "2026-06-23",
      "custo": 0.0,
      "chamadas": 48
    },
    {
      "mcp": "oplab-mcp-server",
      "dia": "2026-06-17",
      "custo": 1.07,
      "chamadas": 67
    },
    {
      "mcp": "oplab-mcp-server",
      "dia": "2026-06-22",
      "custo": 0.01,
      "chamadas": 54
    },
    {
      "mcp": "oplab-mcp-server",
      "dia": "2026-06-18",
      "custo": 0.0,
      "chamadas": 12
    },
    {
      "mcp": "oplab-mcp-server",
      "dia": "2026-06-15",
      "custo": 3.18,
      "chamadas": 171
    },
    {
      "mcp": "oplab-mcp-server",
      "dia": "2026-06-16",
      "custo": 2.33,
      "chamadas": 62
    },
    {
      "mcp": "oplab-mcp-server",
      "dia": "2026-06-12",
      "custo": 1.83,
      "chamadas": 40
    },
    {
      "mcp": "oplab-mcp-server",
      "dia": "2026-06-19",
      "custo": 0.0,
      "chamadas": 29
    },
    {
      "mcp": "oplab-mcp-server",
      "dia": "2026-06-25",
      "custo": 0.03,
      "chamadas": 57
    },
    {
      "mcp": "oplab-sheets-mcp",
      "dia": "2026-06-13",
      "custo": 1.61,
      "chamadas": 47
    },
    {
      "mcp": "oplab-sheets-mcp",
      "dia": "2026-06-20",
      "custo": 0.0,
      "chamadas": 20
    },
    {
      "mcp": "oplab-sheets-mcp",
      "dia": "2026-06-24",
      "custo": 0.01,
      "chamadas": 64
    },
    {
      "mcp": "oplab-sheets-mcp",
      "dia": "2026-06-23",
      "custo": 0.0,
      "chamadas": 74
    },
    {
      "mcp": "oplab-sheets-mcp",
      "dia": "2026-06-17",
      "custo": 1.06,
      "chamadas": 74
    },
    {
      "mcp": "oplab-sheets-mcp",
      "dia": "2026-06-22",
      "custo": 0.0,
      "chamadas": 24
    },
    {
      "mcp": "oplab-sheets-mcp",
      "dia": "2026-06-18",
      "custo": 0.0,
      "chamadas": 14
    },
    {
      "mcp": "oplab-sheets-mcp",
      "dia": "2026-06-15",
      "custo": 3.04,
      "chamadas": 98
    },
    {
      "mcp": "oplab-sheets-mcp",
      "dia": "2026-06-16",
      "custo": 2.3,
      "chamadas": 65
    },
    {
      "mcp": "oplab-sheets-mcp",
      "dia": "2026-06-12",
      "custo": 1.89,
      "chamadas": 49
    },
    {
      "mcp": "oplab-sheets-mcp",
      "dia": "2026-06-19",
      "custo": 0.0,
      "chamadas": 21
    },
    {
      "mcp": "oplab-sheets-mcp",
      "dia": "2026-06-25",
      "custo": 0.01,
      "chamadas": 36
    }
  ],
  "by_calls": [
    {
      "mcp": "oplab-mcp-server",
      "dia": "2026-06-25",
      "chamadas": 57
    },
    {
      "mcp": "oplab-mcp-server",
      "dia": "2026-06-24",
      "chamadas": 147
    },
    {
      "mcp": "oplab-mcp-server",
      "dia": "2026-06-23",
      "chamadas": 48
    },
    {
      "mcp": "oplab-mcp-server",
      "dia": "2026-06-22",
      "chamadas": 54
    },
    {
      "mcp": "oplab-mcp-server",
      "dia": "2026-06-20",
      "chamadas": 15
    },
    {
      "mcp": "oplab-mcp-server",
      "dia": "2026-06-19",
      "chamadas": 29
    },
    {
      "mcp": "oplab-mcp-server",
      "dia": "2026-06-18",
      "chamadas": 12
    },
    {
      "mcp": "oplab-mcp-server",
      "dia": "2026-06-17",
      "chamadas": 67
    },
    {
      "mcp": "oplab-mcp-server",
      "dia": "2026-06-16",
      "chamadas": 62
    },
    {
      "mcp": "oplab-mcp-server",
      "dia": "2026-06-15",
      "chamadas": 171
    },
    {
      "mcp": "oplab-mcp-server",
      "dia": "2026-06-13",
      "chamadas": 15
    },
    {
      "mcp": "oplab-mcp-server",
      "dia": "2026-06-12",
      "chamadas": 40
    },
    {
      "mcp": "oplab-sheets-mcp",
      "dia": "2026-06-25",
      "chamadas": 36
    },
    {
      "mcp": "oplab-sheets-mcp",
      "dia": "2026-06-24",
      "chamadas": 64
    },
    {
      "mcp": "oplab-sheets-mcp",
      "dia": "2026-06-23",
      "chamadas": 74
    },
    {
      "mcp": "oplab-sheets-mcp",
      "dia": "2026-06-22",
      "chamadas": 24
    },
    {
      "mcp": "oplab-sheets-mcp",
      "dia": "2026-06-20",
      "chamadas": 20
    },
    {
      "mcp": "oplab-sheets-mcp",
      "dia": "2026-06-19",
      "chamadas": 21
    },
    {
      "mcp": "oplab-sheets-mcp",
      "dia": "2026-06-18",
      "chamadas": 14
    },
    {
      "mcp": "oplab-sheets-mcp",
      "dia": "2026-06-17",
      "chamadas": 74
    },
    {
      "mcp": "oplab-sheets-mcp",
      "dia": "2026-06-16",
      "chamadas": 65
    },
    {
      "mcp": "oplab-sheets-mcp",
      "dia": "2026-06-15",
      "chamadas": 98
    },
    {
      "mcp": "oplab-sheets-mcp",
      "dia": "2026-06-13",
      "chamadas": 47
    },
    {
      "mcp": "oplab-sheets-mcp",
      "dia": "2026-06-12",
      "chamadas": 49
    }
  ],
  "by_service": [
    {
      "servico": "Cloud Run (estimado)",
      "custo_liquido": 18.39
    }
  ],
  "by_sku": [],
  "by_day": [
    {
      "dia": "2026-06-12",
      "custo_liquido": 3.71
    },
    {
      "dia": "2026-06-13",
      "custo_liquido": 1.61
    },
    {
      "dia": "2026-06-15",
      "custo_liquido": 6.21
    },
    {
      "dia": "2026-06-16",
      "custo_liquido": 4.63
    },
    {
      "dia": "2026-06-17",
      "custo_liquido": 2.13
    },
    {
      "dia": "2026-06-18",
      "custo_liquido": 0.0
    },
    {
      "dia": "2026-06-19",
      "custo_liquido": 0.01
    },
    {
      "dia": "2026-06-20",
      "custo_liquido": 0.0
    },
    {
      "dia": "2026-06-22",
      "custo_liquido": 0.01
    },
    {
      "dia": "2026-06-23",
      "custo_liquido": 0.01
    },
    {
      "dia": "2026-06-24",
      "custo_liquido": 0.03
    },
    {
      "dia": "2026-06-25",
      "custo_liquido": 0.03
    }
  ],
  "by_project": []
}